{
  "song_id": "37b5ac342dc0f7d4",
  "title": "我們高舉耶穌的名",
  "album": "放晴了",
  "composer": "陳麒安",
  "lyricist": "游智婷",
  "series": "兒童敬拜讚美 (11)",
  "key": "C-D",
  "spotify_id": "3ibL2ZHzkKRb49EsOVe12C",
  "spotify_title": "我們高舉耶穌的名",
  "youtube_id": "IIttSnnuwj4",
  "youtube_title": "【Mighty / 你們要讚美耶和華 / 我們高舉耶穌的名 / 我們等候愛慕耶穌 / 我們的神 / 我全然獻上】｜讚美之泉《天堂敬拜 LIVE》",
  "youtube_url": "https://www.youtube.com/watch?v=IIttSnnuwj4",
  "spotify_url": "https://open.spotify.com/track/3ibL2ZHzkKRb49EsOVe12C",
  "lyrics_clean": "大能的君王 尊貴的君王\n我們敬拜祢 尊崇榮耀祢\n大能的君王 尊貴的君王\n與天使齊聲 高舉祢的名\n我們高舉 高舉祢的名\n我們高舉 榮耀的君王\n尊貴 榮耀 頌讚 能力\n我們高舉耶穌的名\n祢是世界的拯救\n祢是得勝的君王\n祢是明亮的晨星\n祢的國度沒有窮盡",
  "lyrics_tokenized": {
    "version": 1,
    "lines": [
      {
        "line_number": 1,
        "text": "大能的君王 尊貴的君王",
        "tokens": [
          {
            "id": "37b5ac342dc0f7d4:1:0",
            "position": 0,
            "type": "hanzi",
            "surface": "大",
            "lemma": "大",
            "traditional": "大",
            "simplified": "大",
            "pinyin": "da4"
          },
          {
            "id": "37b5ac342dc0f7d4:1:1",
            "position": 1,
            "type": "hanzi",
            "surface": "能",
            "lemma": "能",
            "traditional": "能",
            "simplified": "能",
            "pinyin": "neng2"
          },
          {
            "id": "37b5ac342dc0f7d4:1:2",
            "position": 2,
            "type": "hanzi",
            "surface": "的",
            "lemma": "的",
            "traditional": "的",
            "simplified": "的",
            "pinyin": "de"
          },
          {
            "id": "37b5ac342dc0f7d4:1:3",
            "position": 3,
            "type": "hanzi",
            "surface": "君",
            "lemma": "君",
            "traditional": "君",
            "simplified": "君",
            "pinyin": "jun1"
          },
          {
            "id": "37b5ac342dc0f7d4:1:4",
            "position": 4,
            "type": "hanzi",
            "surface": "王",
            "lemma": "王",
            "traditional": "王",
            "simplified": "王",
            "pinyin": "wang2"
          },
          {
            "id": null,
            "position": 5,
            "type": "word",
            "surface": " ",
            "lemma": " ",
            "traditional": null,
            "simplified": null,
            "pinyin": null
          },
          {
            "id": "37b5ac342dc0f7d4:1:6",
            "position": 6,
            "type": "hanzi",
            "surface": "尊",
            "lemma": "尊",
            "traditional": "尊",
            "simplified": "尊",
            "pinyin": "zun1"
          },
          {
            "id": "37b5ac342dc0f7d4:1:7",
            "position": 7,
            "type": "hanzi",
            "surface": "貴",
            "lemma": "贵",
            "traditional": "貴",
            "simplified": "贵",
            "pinyin": "gui4"
          },
          {
            "id": "37b5ac342dc0f7d4:1:8",
            "position": 8,
            "type": "hanzi",
            "surface": "的",
            "lemma": "的",
            "traditional": "的",
            "simplified": "的",
            "pinyin": "de"
          },
          {
            "id": "37b5ac342dc0f7d4:1:9",
            "position": 9,
            "type": "hanzi",
            "surface": "君",
            "lemma": "君",
            "traditional": "君",
            "simplified": "君",
            "pinyin": "jun1"
          },
          {
            "id": "37b5ac342dc0f7d4:1:10",
            "position": 10,
            "type": "hanzi",
            "surface": "王",
            "lemma": "王",
            "traditional": "王",
            "simplified": "王",
            "pinyin": "wang2"
          }
        ],
        "render_groups": [
          {
            "term_id": "1dc59c4a3024fc68",
            "term": "大能",
            "start": 0,
            "end": 1
          },
          {
            "term_id": "228726b1bf789a59",
            "term": "君王",
            "start": 3,
            "end": 4
          },
          {
            "term_id": "f37ad8e4bdc394aa",
            "term": "尊貴",
            "start": 6,
            "end": 7
          },
          {
            "term_id": "228726b1bf789a59",
            "term": "君王",
            "start": 9,
            "end": 10
          }
        ]
      },
      {
        "line_number": 2,
        "text": "我們敬拜祢 尊崇榮耀祢",
        "tokens": [
          {
            "id": "37b5ac342dc0f7d4:2:0",
            "position": 0,
            "type": "hanzi",
            "surface": "我",
            "lemma": "我",
            "traditional": "我",
            "simplified": "我",
            "pinyin": "wo3"
          },
          {
            "id": "37b5ac342dc0f7d4:2:1",
            "position": 1,
            "type": "hanzi",
            "surface": "們",
            "lemma": "们",
            "traditional": "們",
            "simplified": "们",
            "pinyin": "men"
          },
          {
            "id": "37b5ac342dc0f7d4:2:2",
            "position": 2,
            "type": "hanzi",
            "surface": "敬",
            "lemma": "敬",
            "traditional": "敬",
            "simplified": "敬",
            "pinyin": "jing4"
          },
          {
            "id": "37b5ac342dc0f7d4:2:3",
            "position": 3,
            "type": "hanzi",
            "surface": "拜",
            "lemma": "拜",
            "traditional": "拜",
            "simplified": "拜",
            "pinyin": "bai4"
          },
          {
            "id": "37b5ac342dc0f7d4:2:4",
            "position": 4,
            "type": "hanzi",
            "surface": "祢",
            "lemma": "祢",
            "traditional": "禰",
            "simplified": "祢",
            "pinyin": "mi2"
          },
          {
            "id": null,
            "position": 5,
            "type": "word",
            "surface": " ",
            "lemma": " ",
            "traditional": null,
            "simplified": null,
            "pinyin": null
          },
          {
            "id": "37b5ac342dc0f7d4:2:6",
            "position": 6,
            "type": "hanzi",
            "surface": "尊",
            "lemma": "尊",
            "traditional": "尊",
            "simplified": "尊",
            "pinyin": "zun1"
          },
          {
            "id": "37b5ac342dc0f7d4:2:7",
            "position": 7,
            "type": "hanzi",
            "surface": "崇",
            "lemma": "崇",
            "traditional": "崇",
            "simplified": "崇",
            "pinyin": "chong2"
          },
          {
            "id": "37b5ac342dc0f7d4:2:8",
            "position": 8,
            "type": "hanzi",
            "surface": "榮",
            "lemma": "荣",
            "traditional": "榮",
            "simplified": "荣",
            "pinyin": "rong2"
          },
          {
            "id": "37b5ac342dc0f7d4:2:9",
            "position": 9,
            "type": "hanzi",
            "surface": "耀",
            "lemma": "耀",
            "traditional": "耀",
            "simplified": "耀",
            "pinyin": "yao4"
          },
          {
            "id": "37b5ac342dc0f7d4:2:10",
            "position": 10,
            "type": "hanzi",
            "surface": "祢",
            "lemma": "祢",
            "traditional": "禰",
            "simplified": "祢",
            "pinyin": "mi2"
          }
        ],
        "render_groups": [
          {
            "term_id": "40d230054b141270",
            "term": "敬拜",
            "start": 2,
            "end": 3
          },
          {
            "term_id": "4b48588faae6913d",
            "term": "尊崇",
            "start": 6,
            "end": 7
          },
          {
            "term_id": "4f0eea448c61f8b9",
            "term": "榮耀",
            "start": 8,
            "end": 9
          }
        ]
      },
      {
        "line_number": 3,
        "text": "大能的君王 尊貴的君王",
        "tokens": [
          {
            "id": "37b5ac342dc0f7d4:3:0",
            "position": 0,
            "type": "hanzi",
            "surface": "大",
            "lemma": "大",
            "traditional": "大",
            "simplified": "大",
            "pinyin": "da4"
          },
          {
            "id": "37b5ac342dc0f7d4:3:1",
            "position": 1,
            "type": "hanzi",
            "surface": "能",
            "lemma": "能",
            "traditional": "能",
            "simplified": "能",
            "pinyin": "neng2"
          },
          {
            "id": "37b5ac342dc0f7d4:3:2",
            "position": 2,
            "type": "hanzi",
            "surface": "的",
            "lemma": "的",
            "traditional": "的",
            "simplified": "的",
            "pinyin": "de"
          },
          {
            "id": "37b5ac342dc0f7d4:3:3",
            "position": 3,
            "type": "hanzi",
            "surface": "君",
            "lemma": "君",
            "traditional": "君",
            "simplified": "君",
            "pinyin": "jun1"
          },
          {
            "id": "37b5ac342dc0f7d4:3:4",
            "position": 4,
            "type": "hanzi",
            "surface": "王",
            "lemma": "王",
            "traditional": "王",
            "simplified": "王",
            "pinyin": "wang2"
          },
          {
            "id": null,
            "position": 5,
            "type": "word",
            "surface": " ",
            "lemma": " ",
            "traditional": null,
            "simplified": null,
            "pinyin": null
          },
          {
            "id": "37b5ac342dc0f7d4:3:6",
            "position": 6,
            "type": "hanzi",
            "surface": "尊",
            "lemma": "尊",
            "traditional": "尊",
            "simplified": "尊",
            "pinyin": "zun1"
          },
          {
            "id": "37b5ac342dc0f7d4:3:7",
            "position": 7,
            "type": "hanzi",
            "surface": "貴",
            "lemma": "贵",
            "traditional": "貴",
            "simplified": "贵",
            "pinyin": "gui4"
          },
          {
            "id": "37b5ac342dc0f7d4:3:8",
            "position": 8,
            "type": "hanzi",
            "surface": "的",
            "lemma": "的",
            "traditional": "的",
            "simplified": "的",
            "pinyin": "de"
          },
          {
            "id": "37b5ac342dc0f7d4:3:9",
            "position": 9,
            "type": "hanzi",
            "surface": "君",
            "lemma": "君",
            "traditional": "君",
            "simplified": "君",
            "pinyin": "jun1"
          },
          {
            "id": "37b5ac342dc0f7d4:3:10",
            "position": 10,
            "type": "hanzi",
            "surface": "王",
            "lemma": "王",
            "traditional": "王",
            "simplified": "王",
            "pinyin": "wang2"
          }
        ],
        "render_groups": [
          {
            "term_id": "1dc59c4a3024fc68",
            "term": "大能",
            "start": 0,
            "end": 1
          },
          {
            "term_id": "228726b1bf789a59",
            "term": "君王",
            "start": 3,
            "end": 4
          },
          {
            "term_id": "f37ad8e4bdc394aa",
            "term": "尊貴",
            "start": 6,
            "end": 7
          },
          {
            "term_id": "228726b1bf789a59",
            "term": "君王",
            "start": 9,
            "end": 10
          }
        ]
      },
      {
        "line_number": 4,
        "text": "與天使齊聲 高舉祢的名",
        "tokens": [
          {
            "id": "37b5ac342dc0f7d4:4:0",
            "position": 0,
            "type": "hanzi",
            "surface": "與",
            "lemma": "与",
            "traditional": "與",
            "simplified": "与",
            "pinyin": "yu3"
          },
          {
            "id": "37b5ac342dc0f7d4:4:1",
            "position": 1,
            "type": "hanzi",
            "surface": "天",
            "lemma": "天",
            "traditional": "天",
            "simplified": "天",
            "pinyin": "tian1"
          },
          {
            "id": "37b5ac342dc0f7d4:4:2",
            "position": 2,
            "type": "hanzi",
            "surface": "使",
            "lemma": "使",
            "traditional": "使",
            "simplified": "使",
            "pinyin": "shi3"
          },
          {
            "id": "37b5ac342dc0f7d4:4:3",
            "position": 3,
            "type": "hanzi",
            "surface": "齊",
            "lemma": "齐",
            "traditional": "齊",
            "simplified": "齐",
            "pinyin": "qi2"
          },
          {
            "id": "37b5ac342dc0f7d4:4:4",
            "position": 4,
            "type": "hanzi",
            "surface": "聲",
            "lemma": "声",
            "traditional": "聲",
            "simplified": "声",
            "pinyin": "sheng1"
          },
          {
            "id": null,
            "position": 5,
            "type": "word",
            "surface": " ",
            "lemma": " ",
            "traditional": null,
            "simplified": null,
            "pinyin": null
          },
          {
            "id": "37b5ac342dc0f7d4:4:6",
            "position": 6,
            "type": "hanzi",
            "surface": "高",
            "lemma": "高",
            "traditional": "高",
            "simplified": "高",
            "pinyin": "gao1"
          },
          {
            "id": "37b5ac342dc0f7d4:4:7",
            "position": 7,
            "type": "hanzi",
            "surface": "舉",
            "lemma": "举",
            "traditional": "舉",
            "simplified": "举",
            "pinyin": "ju3"
          },
          {
            "id": "37b5ac342dc0f7d4:4:8",
            "position": 8,
            "type": "hanzi",
            "surface": "祢",
            "lemma": "祢",
            "traditional": "禰",
            "simplified": "祢",
            "pinyin": "mi2"
          },
          {
            "id": "37b5ac342dc0f7d4:4:9",
            "position": 9,
            "type": "hanzi",
            "surface": "的",
            "lemma": "的",
            "traditional": "的",
            "simplified": "的",
            "pinyin": "de"
          },
          {
            "id": "37b5ac342dc0f7d4:4:10",
            "position": 10,
            "type": "hanzi",
            "surface": "名",
            "lemma": "名",
            "traditional": "名",
            "simplified": "名",
            "pinyin": "ming2"
          }
        ],
        "render_groups": []
      },
      {
        "line_number": 5,
        "text": "我們高舉 高舉祢的名",
        "tokens": [
          {
            "id": "37b5ac342dc0f7d4:5:0",
            "position": 0,
            "type": "hanzi",
            "surface": "我",
            "lemma": "我",
            "traditional": "我",
            "simplified": "我",
            "pinyin": "wo3"
          },
          {
            "id": "37b5ac342dc0f7d4:5:1",
            "position": 1,
            "type": "hanzi",
            "surface": "們",
            "lemma": "们",
            "traditional": "們",
            "simplified": "们",
            "pinyin": "men"
          },
          {
            "id": "37b5ac342dc0f7d4:5:2",
            "position": 2,
            "type": "hanzi",
            "surface": "高",
            "lemma": "高",
            "traditional": "高",
            "simplified": "高",
            "pinyin": "gao1"
          },
          {
            "id": "37b5ac342dc0f7d4:5:3",
            "position": 3,
            "type": "hanzi",
            "surface": "舉",
            "lemma": "举",
            "traditional": "舉",
            "simplified": "举",
            "pinyin": "ju3"
          },
          {
            "id": null,
            "position": 4,
            "type": "word",
            "surface": " ",
            "lemma": " ",
            "traditional": null,
            "simplified": null,
            "pinyin": null
          },
          {
            "id": "37b5ac342dc0f7d4:5:5",
            "position": 5,
            "type": "hanzi",
            "surface": "高",
            "lemma": "高",
            "traditional": "高",
            "simplified": "高",
            "pinyin": "gao1"
          },
          {
            "id": "37b5ac342dc0f7d4:5:6",
            "position": 6,
            "type": "hanzi",
            "surface": "舉",
            "lemma": "举",
            "traditional": "舉",
            "simplified": "举",
            "pinyin": "ju3"
          },
          {
            "id": "37b5ac342dc0f7d4:5:7",
            "position": 7,
            "type": "hanzi",
            "surface": "祢",
            "lemma": "祢",
            "traditional": "禰",
            "simplified": "祢",
            "pinyin": "mi2"
          },
          {
            "id": "37b5ac342dc0f7d4:5:8",
            "position": 8,
            "type": "hanzi",
            "surface": "的",
            "lemma": "的",
            "traditional": "的",
            "simplified": "的",
            "pinyin": "de"
          },
          {
            "id": "37b5ac342dc0f7d4:5:9",
            "position": 9,
            "type": "hanzi",
            "surface": "名",
            "lemma": "名",
            "traditional": "名",
            "simplified": "名",
            "pinyin": "ming2"
          }
        ],
        "render_groups": []
      },
      {
        "line_number": 6,
        "text": "我們高舉 榮耀的君王",
        "tokens": [
          {
            "id": "37b5ac342dc0f7d4:6:0",
            "position": 0,
            "type": "hanzi",
            "surface": "我",
            "lemma": "我",
            "traditional": "我",
            "simplified": "我",
            "pinyin": "wo3"
          },
          {
            "id": "37b5ac342dc0f7d4:6:1",
            "position": 1,
            "type": "hanzi",
            "surface": "們",
            "lemma": "们",
            "traditional": "們",
            "simplified": "们",
            "pinyin": "men"
          },
          {
            "id": "37b5ac342dc0f7d4:6:2",
            "position": 2,
            "type": "hanzi",
            "surface": "高",
            "lemma": "高",
            "traditional": "高",
            "simplified": "高",
            "pinyin": "gao1"
          },
          {
            "id": "37b5ac342dc0f7d4:6:3",
            "position": 3,
            "type": "hanzi",
            "surface": "舉",
            "lemma": "举",
            "traditional": "舉",
            "simplified": "举",
            "pinyin": "ju3"
          },
          {
            "id": null,
            "position": 4,
            "type": "word",
            "surface": " ",
            "lemma": " ",
            "traditional": null,
            "simplified": null,
            "pinyin": null
          },
          {
            "id": "37b5ac342dc0f7d4:6:5",
            "position": 5,
            "type": "hanzi",
            "surface": "榮",
            "lemma": "荣",
            "traditional": "榮",
            "simplified": "荣",
            "pinyin": "rong2"
          },
          {
            "id": "37b5ac342dc0f7d4:6:6",
            "position": 6,
            "type": "hanzi",
            "surface": "耀",
            "lemma": "耀",
            "traditional": "耀",
            "simplified": "耀",
            "pinyin": "yao4"
          },
          {
            "id": "37b5ac342dc0f7d4:6:7",
            "position": 7,
            "type": "hanzi",
            "surface": "的",
            "lemma": "的",
            "traditional": "的",
            "simplified": "的",
            "pinyin": "de"
          },
          {
            "id": "37b5ac342dc0f7d4:6:8",
            "position": 8,
            "type": "hanzi",
            "surface": "君",
            "lemma": "君",
            "traditional": "君",
            "simplified": "君",
            "pinyin": "jun1"
          },
          {
            "id": "37b5ac342dc0f7d4:6:9",
            "position": 9,
            "type": "hanzi",
            "surface": "王",
            "lemma": "王",
            "traditional": "王",
            "simplified": "王",
            "pinyin": "wang2"
          }
        ],
        "render_groups": [
          {
            "term_id": "4f0eea448c61f8b9",
            "term": "榮耀",
            "start": 5,
            "end": 6
          },
          {
            "term_id": "228726b1bf789a59",
            "term": "君王",
            "start": 8,
            "end": 9
          }
        ]
      },
      {
        "line_number": 7,
        "text": "尊貴 榮耀 頌讚 能力",
        "tokens": [
          {
            "id": "37b5ac342dc0f7d4:7:0",
            "position": 0,
            "type": "hanzi",
            "surface": "尊",
            "lemma": "尊",
            "traditional": "尊",
            "simplified": "尊",
            "pinyin": "zun1"
          },
          {
            "id": "37b5ac342dc0f7d4:7:1",
            "position": 1,
            "type": "hanzi",
            "surface": "貴",
            "lemma": "贵",
            "traditional": "貴",
            "simplified": "贵",
            "pinyin": "gui4"
          },
          {
            "id": null,
            "position": 2,
            "type": "word",
            "surface": " ",
            "lemma": " ",
            "traditional": null,
            "simplified": null,
            "pinyin": null
          },
          {
            "id": "37b5ac342dc0f7d4:7:3",
            "position": 3,
            "type": "hanzi",
            "surface": "榮",
            "lemma": "荣",
            "traditional": "榮",
            "simplified": "荣",
            "pinyin": "rong2"
          },
          {
            "id": "37b5ac342dc0f7d4:7:4",
            "position": 4,
            "type": "hanzi",
            "surface": "耀",
            "lemma": "耀",
            "traditional": "耀",
            "simplified": "耀",
            "pinyin": "yao4"
          },
          {
            "id": null,
            "position": 5,
            "type": "word",
            "surface": " ",
            "lemma": " ",
            "traditional": null,
            "simplified": null,
            "pinyin": null
          },
          {
            "id": "37b5ac342dc0f7d4:7:6",
            "position": 6,
            "type": "hanzi",
            "surface": "頌",
            "lemma": "颂",
            "traditional": "頌",
            "simplified": "颂",
            "pinyin": "song4"
          },
          {
            "id": "37b5ac342dc0f7d4:7:7",
            "position": 7,
            "type": "hanzi",
            "surface": "讚",
            "lemma": "赞",
            "traditional": "讚",
            "simplified": "赞",
            "pinyin": "zan4"
          },
          {
            "id": null,
            "position": 8,
            "type": "word",
            "surface": " ",
            "lemma": " ",
            "traditional": null,
            "simplified": null,
            "pinyin": null
          },
          {
            "id": "37b5ac342dc0f7d4:7:9",
            "position": 9,
            "type": "hanzi",
            "surface": "能",
            "lemma": "能",
            "traditional": "能",
            "simplified": "能",
            "pinyin": "neng2"
          },
          {
            "id": "37b5ac342dc0f7d4:7:10",
            "position": 10,
            "type": "hanzi",
            "surface": "力",
            "lemma": "力",
            "traditional": "力",
            "simplified": "力",
            "pinyin": "li4"
          }
        ],
        "render_groups": [
          {
            "term_id": "f37ad8e4bdc394aa",
            "term": "尊貴",
            "start": 0,
            "end": 1
          },
          {
            "term_id": "4f0eea448c61f8b9",
            "term": "榮耀",
            "start": 3,
            "end": 4
          },
          {
            "term_id": "6743820193b7d2fb",
            "term": "頌讚",
            "start": 6,
            "end": 7
          }
        ]
      },
      {
        "line_number": 8,
        "text": "我們高舉耶穌的名",
        "tokens": [
          {
            "id": "37b5ac342dc0f7d4:8:0",
            "position": 0,
            "type": "hanzi",
            "surface": "我",
            "lemma": "我",
            "traditional": "我",
            "simplified": "我",
            "pinyin": "wo3"
          },
          {
            "id": "37b5ac342dc0f7d4:8:1",
            "position": 1,
            "type": "hanzi",
            "surface": "們",
            "lemma": "们",
            "traditional": "們",
            "simplified": "们",
            "pinyin": "men"
          },
          {
            "id": "37b5ac342dc0f7d4:8:2",
            "position": 2,
            "type": "hanzi",
            "surface": "高",
            "lemma": "高",
            "traditional": "高",
            "simplified": "高",
            "pinyin": "gao1"
          },
          {
            "id": "37b5ac342dc0f7d4:8:3",
            "position": 3,
            "type": "hanzi",
            "surface": "舉",
            "lemma": "举",
            "traditional": "舉",
            "simplified": "举",
            "pinyin": "ju3"
          },
          {
            "id": "37b5ac342dc0f7d4:8:4",
            "position": 4,
            "type": "hanzi",
            "surface": "耶",
            "lemma": "耶",
            "traditional": "耶",
            "simplified": "耶",
            "pinyin": "ye2"
          },
          {
            "id": "37b5ac342dc0f7d4:8:5",
            "position": 5,
            "type": "hanzi",
            "surface": "穌",
            "lemma": "稣",
            "traditional": "穌",
            "simplified": "稣",
            "pinyin": "su1"
          },
          {
            "id": "37b5ac342dc0f7d4:8:6",
            "position": 6,
            "type": "hanzi",
            "surface": "的",
            "lemma": "的",
            "traditional": "的",
            "simplified": "的",
            "pinyin": "de"
          },
          {
            "id": "37b5ac342dc0f7d4:8:7",
            "position": 7,
            "type": "hanzi",
            "surface": "名",
            "lemma": "名",
            "traditional": "名",
            "simplified": "名",
            "pinyin": "ming2"
          }
        ],
        "render_groups": []
      },
      {
        "line_number": 9,
        "text": "祢是世界的拯救",
        "tokens": [
          {
            "id": "37b5ac342dc0f7d4:9:0",
            "position": 0,
            "type": "hanzi",
            "surface": "祢",
            "lemma": "祢",
            "traditional": "禰",
            "simplified": "祢",
            "pinyin": "mi2"
          },
          {
            "id": "37b5ac342dc0f7d4:9:1",
            "position": 1,
            "type": "hanzi",
            "surface": "是",
            "lemma": "是",
            "traditional": "是",
            "simplified": "是",
            "pinyin": "shi4"
          },
          {
            "id": "37b5ac342dc0f7d4:9:2",
            "position": 2,
            "type": "hanzi",
            "surface": "世",
            "lemma": "世",
            "traditional": "世",
            "simplified": "世",
            "pinyin": "shi4"
          },
          {
            "id": "37b5ac342dc0f7d4:9:3",
            "position": 3,
            "type": "hanzi",
            "surface": "界",
            "lemma": "界",
            "traditional": "界",
            "simplified": "界",
            "pinyin": "jie4"
          },
          {
            "id": "37b5ac342dc0f7d4:9:4",
            "position": 4,
            "type": "hanzi",
            "surface": "的",
            "lemma": "的",
            "traditional": "的",
            "simplified": "的",
            "pinyin": "de"
          },
          {
            "id": "37b5ac342dc0f7d4:9:5",
            "position": 5,
            "type": "hanzi",
            "surface": "拯",
            "lemma": "拯",
            "traditional": "拯",
            "simplified": "拯",
            "pinyin": "zheng3"
          },
          {
            "id": "37b5ac342dc0f7d4:9:6",
            "position": 6,
            "type": "hanzi",
            "surface": "救",
            "lemma": "救",
            "traditional": "救",
            "simplified": "救",
            "pinyin": "jiu4"
          }
        ],
        "render_groups": []
      },
      {
        "line_number": 10,
        "text": "祢是得勝的君王",
        "tokens": [
          {
            "id": "37b5ac342dc0f7d4:10:0",
            "position": 0,
            "type": "hanzi",
            "surface": "祢",
            "lemma": "祢",
            "traditional": "禰",
            "simplified": "祢",
            "pinyin": "mi2"
          },
          {
            "id": "37b5ac342dc0f7d4:10:1",
            "position": 1,
            "type": "hanzi",
            "surface": "是",
            "lemma": "是",
            "traditional": "是",
            "simplified": "是",
            "pinyin": "shi4"
          },
          {
            "id": "37b5ac342dc0f7d4:10:2",
            "position": 2,
            "type": "hanzi",
            "surface": "得",
            "lemma": "得",
            "traditional": "得",
            "simplified": "得",
            "pinyin": "de2"
          },
          {
            "id": "37b5ac342dc0f7d4:10:3",
            "position": 3,
            "type": "hanzi",
            "surface": "勝",
            "lemma": "胜",
            "traditional": "勝",
            "simplified": "胜",
            "pinyin": "sheng4"
          },
          {
            "id": "37b5ac342dc0f7d4:10:4",
            "position": 4,
            "type": "hanzi",
            "surface": "的",
            "lemma": "的",
            "traditional": "的",
            "simplified": "的",
            "pinyin": "de"
          },
          {
            "id": "37b5ac342dc0f7d4:10:5",
            "position": 5,
            "type": "hanzi",
            "surface": "君",
            "lemma": "君",
            "traditional": "君",
            "simplified": "君",
            "pinyin": "jun1"
          },
          {
            "id": "37b5ac342dc0f7d4:10:6",
            "position": 6,
            "type": "hanzi",
            "surface": "王",
            "lemma": "王",
            "traditional": "王",
            "simplified": "王",
            "pinyin": "wang2"
          }
        ],
        "render_groups": [
          {
            "term_id": "228726b1bf789a59",
            "term": "君王",
            "start": 5,
            "end": 6
          }
        ]
      },
      {
        "line_number": 11,
        "text": "祢是明亮的晨星",
        "tokens": [
          {
            "id": "37b5ac342dc0f7d4:11:0",
            "position": 0,
            "type": "hanzi",
            "surface": "祢",
            "lemma": "祢",
            "traditional": "禰",
            "simplified": "祢",
            "pinyin": "mi2"
          },
          {
            "id": "37b5ac342dc0f7d4:11:1",
            "position": 1,
            "type": "hanzi",
            "surface": "是",
            "lemma": "是",
            "traditional": "是",
            "simplified": "是",
            "pinyin": "shi4"
          },
          {
            "id": "37b5ac342dc0f7d4:11:2",
            "position": 2,
            "type": "hanzi",
            "surface": "明",
            "lemma": "明",
            "traditional": "明",
            "simplified": "明",
            "pinyin": "ming2"
          },
          {
            "id": "37b5ac342dc0f7d4:11:3",
            "position": 3,
            "type": "hanzi",
            "surface": "亮",
            "lemma": "亮",
            "traditional": "亮",
            "simplified": "亮",
            "pinyin": "liang4"
          },
          {
            "id": "37b5ac342dc0f7d4:11:4",
            "position": 4,
            "type": "hanzi",
            "surface": "的",
            "lemma": "的",
            "traditional": "的",
            "simplified": "的",
            "pinyin": "de"
          },
          {
            "id": "37b5ac342dc0f7d4:11:5",
            "position": 5,
            "type": "hanzi",
            "surface": "晨",
            "lemma": "晨",
            "traditional": "晨",
            "simplified": "晨",
            "pinyin": "chen2"
          },
          {
            "id": "37b5ac342dc0f7d4:11:6",
            "position": 6,
            "type": "hanzi",
            "surface": "星",
            "lemma": "星",
            "traditional": "星",
            "simplified": "星",
            "pinyin": "xing1"
          }
        ],
        "render_groups": []
      },
      {
        "line_number": 12,
        "text": "祢的國度沒有窮盡",
        "tokens": [
          {
            "id": "37b5ac342dc0f7d4:12:0",
            "position": 0,
            "type": "hanzi",
            "surface": "祢",
            "lemma": "祢",
            "traditional": "禰",
            "simplified": "祢",
            "pinyin": "mi2"
          },
          {
            "id": "37b5ac342dc0f7d4:12:1",
            "position": 1,
            "type": "hanzi",
            "surface": "的",
            "lemma": "的",
            "traditional": "的",
            "simplified": "的",
            "pinyin": "de"
          },
          {
            "id": "37b5ac342dc0f7d4:12:2",
            "position": 2,
            "type": "hanzi",
            "surface": "國",
            "lemma": "国",
            "traditional": "國",
            "simplified": "国",
            "pinyin": "guo2"
          },
          {
            "id": "37b5ac342dc0f7d4:12:3",
            "position": 3,
            "type": "hanzi",
            "surface": "度",
            "lemma": "度",
            "traditional": "度",
            "simplified": "度",
            "pinyin": "du4"
          },
          {
            "id": "37b5ac342dc0f7d4:12:4",
            "position": 4,
            "type": "hanzi",
            "surface": "沒",
            "lemma": "没",
            "traditional": "沒",
            "simplified": "没",
            "pinyin": "mei2"
          },
          {
            "id": "37b5ac342dc0f7d4:12:5",
            "position": 5,
            "type": "hanzi",
            "surface": "有",
            "lemma": "有",
            "traditional": "有",
            "simplified": "有",
            "pinyin": "you3"
          },
          {
            "id": "37b5ac342dc0f7d4:12:6",
            "position": 6,
            "type": "hanzi",
            "surface": "窮",
            "lemma": "穷",
            "traditional": "窮",
            "simplified": "穷",
            "pinyin": "qiong2"
          },
          {
            "id": "37b5ac342dc0f7d4:12:7",
            "position": 7,
            "type": "hanzi",
            "surface": "盡",
            "lemma": "尽",
            "traditional": "盡",
            "simplified": "尽",
            "pinyin": "jin3"
          }
        ],
        "render_groups": [
          {
            "term_id": "d495d5cd7eeb1cea",
            "term": "國度",
            "start": 2,
            "end": 3
          },
          {
            "term_id": "c98eaeb067f82421",
            "term": "窮盡",
            "start": 6,
            "end": 7
          }
        ]
      }
    ]
  }
}